README.md
setup.py
tinyretry/__init__.py
tinyretry.egg-info/PKG-INFO
tinyretry.egg-info/SOURCES.txt
tinyretry.egg-info/dependency_links.txt
tinyretry.egg-info/top_level.txt